scisample/__init__.py
scisample/base_sampler.py
scisample/best_candidate_sampler.py
scisample/column_list_sampler.py
scisample/config.yaml
scisample/cross_product_sampler.py
scisample/csv_sampler.py
scisample/custom_sampler.py
scisample/interface.py
scisample/list_sampler.py
scisample/random_sampler.py
scisample/samplers.py
scisample/schema.py
scisample/uqpipeline_sampler.py
scisample/utils.py
scisample-1.0.3.data/scripts/pgen_scisample.py
tests/__init__.py
tests/test_import.py
tests/test_samplers.py
tests/test_uqpipeline_samplers.py
tests/test_utils.py
scisample-1.0.3.dist-info/LICENSE
scisample-1.0.3.dist-info/METADATA
scisample-1.0.3.dist-info/NOTICE
scisample-1.0.3.dist-info/WHEEL
scisample-1.0.3.dist-info/top_level.txt
scisample-1.0.3.dist-info/RECORD
