Metadata-Version: 2.1
Name: scisample
Version: 1.0.3
Summary: Parameter sampling for scientific computing
Home-page: https://github.com/LLNL/scisample
Author: Brian Daub, Chris Krenn, Cody Raskin, Jessica Semler
Author-email: daub1@llnl.gov, krenn1@llnl.gov, raskin1@llnl.gov, semler1@llnl.gov
License: MIT License
Classifier: Programming Language :: Python :: 3
Classifier: License :: OSI Approved :: MIT License
Classifier: Operating System :: OS Independent
Requires-Python: >=3.6
License-File: LICENSE
License-File: NOTICE
Requires-Dist: parse
Requires-Dist: numpy
Requires-Dist: cached-property
Provides-Extra: best_candidate
Requires-Dist: pandas ; extra == 'best_candidate'
Requires-Dist: scipy ; extra == 'best_candidate'
Provides-Extra: maestrowf
Requires-Dist: maestrowf ; extra == 'maestrowf'
